microboiler/__init__.py
microboiler/microboiler
microboiler/microboiler.py
microboiler/modules/__init__.py
microboiler/modules/basemodule.py
microboiler/modules/clients/__init__.py
microboiler/modules/clients/angular.py
microboiler/modules/clients/clients.py
microboiler/modules/clients/ionic.py
microboiler/modules/databases/__init__.py
microboiler/modules/databases/mongodb.py
microboiler/modules/databases/mysql.py
microboiler/modules/databases/postgre.py
microboiler/modules/databases/redis.py
microboiler/modules/devops/__init__.py
microboiler/modules/devops/docker.py
microboiler/modules/eventbus/__init__.py
microboiler/modules/eventbus/rabbitmq.py
microboiler/modules/identity/__init__.py
microboiler/modules/identity/identityserver4.py
microboiler/modules/servers/__init__.py
microboiler/modules/servers/nginx.py
microboiler/modules/servers/server.py
microboiler/modules/services/__init__.py
microboiler/modules/services/dotnetapi.py
microboiler/modules/services/nodeapi.py
microboiler/modules/templating/__init__.py
microboiler/modules/templating/csharp.py
microboiler/modules/templating/javascript.py
microboiler/modules/templating/templating.py
microboiler/modules/utils/__init__.py
microboiler/modules/utils/utils.py
microboiler-0.0.8.data/scripts/microboiler
microboiler-0.0.8.dist-info/METADATA
microboiler-0.0.8.dist-info/RECORD
microboiler-0.0.8.dist-info/WHEEL
microboiler-0.0.8.dist-info/top_level.txt
