Metadata-Version: 2.1
Name: microboiler
Version: 0.0.8
Summary: A Python tool for generating various types of microservice architecture projects.
Home-page: https://github.com/DooMachine/microboiler
Author: Okan Aslankan
Author-email: okn.aslnkn@gmail.com
License: UNKNOWN
Project-URL: Bug Reports, https://github.com/DooMachine/microboiler/issues
Project-URL: Funding, https://donate.pypi.org
Project-URL: Source, https://github.com/DooMachine/microboiler/
Keywords: microservices node .net angular ionic docker nginx devops development
Platform: UNKNOWN
Classifier: Development Status :: 3 - Alpha
Classifier: Intended Audience :: Developers
Classifier: Programming Language :: Python :: 3
Classifier: License :: OSI Approved :: MIT License
Classifier: Operating System :: OS Independent
Requires-Dist: pyyaml (==3.12)
Requires-Dist: python-nginx (==1.4.1)
